cs_commons/__init__.py
cs_commons/rewe_rdc_signature.py
cs_commons-0.0.1.dist-info/WHEEL
cs_commons-0.0.1.dist-info/METADATA
cs_commons-0.0.1.dist-info/RECORD
