Metadata-Version: 2.1
Name: cs-commons
Version: 0.0.1
Summary: ChillServices commons
Author-email: Anders Petersson <petersson@chillservices.com>
Requires-Python: >=3.10
Project-URL: Home, https://chillservices.com/
